greeting_package/__init__.py
greeting_package/greeting.py
greeting_package/tests/__init__.py
greeting_package/tests/test_greeting.py
greeting_package-0.1.3.dist-info/LICENSE
greeting_package-0.1.3.dist-info/METADATA
greeting_package-0.1.3.dist-info/WHEEL
greeting_package-0.1.3.dist-info/top_level.txt
greeting_package-0.1.3.dist-info/RECORD
