Metadata-Version: 2.1
Name: greeting-package
Version: 0.1.3
Summary: A simple greeting package
Home-page: https://github.com/osundwajeff/greeting_package
Author: Jeff Osundwa
Author-email: mulamajeff@tuta.io
License: MIT
Classifier: Programming Language :: Python :: 3
Classifier: Programming Language :: Python :: 3.7
Classifier: Programming Language :: Python :: 3.8
Classifier: Programming Language :: Python :: 3.9
Requires-Python: >=3.7
License-File: LICENSE
